Communication_Protocols/SPI/SPI_Master.v
module spi_master (
    input wire clk,
    input wire rst,
    // Chip Select
    input wire en,
    output reg cs,
    // Serial Clock
    output reg sck,
    // Master Out Slave In
    input wire [7:0] ext_command_in,
    input wire [7:0] ext_address_in,
    input wire [7:0] ext_data_in,
    output reg mosi,
    // Master In Slave Out
    input wire miso,
    output wire [7:0] ext_data_out
);
    
    // Serial Clock

    reg clock_count;

    always @(posedge clk) begin
        if (rst) begin
            clock_count <= 0;
        end
        else begin
            if ((current_state == ENABLE) || (current_state == DATA)) begin
                clock_count <= clock_count + 1;
            end
            else begin
                clock_count <= 0;
            end
        end
    end

    // Master Out Slave In

    reg [23:0] data_save;
    reg [23:0] data_count;
    reg data_end;

    always @(posedge clk) begin
        if (rst) begin
            data_save <= 0;
            data_count <= 0;
            data_end <= 0;
        end
        else begin
            if (current_state == DATA) begin
                if (sck == 1) begin
                    data_save <= {data_save[22:0],1'b0};
                    if (data_count == 23) begin
                        data_count <= 0;
                        data_end <= 1;
                    end
                    else begin
                        data_count <= data_count + 1;
                        data_end <= 0;
                    end
                end
                else begin
                    data_save <= data_save;
                    data_count <= data_count;
                    data_end <= 0;
                end
            end
            else begin
                if (ext_command_in == 8'h00) begin
                    data_save <= {ext_command_in,ext_address_in,ext_data_in};
                    data_count <= 0;
                    data_end <= 0;
                end
                else begin
                    data_save <= {ext_command_in,ext_address_in,8'h00};
                    data_count <= 0;
                    data_end <= 0;
                end
            end
        end
    end

    // Master In Slave Out

    reg [7:0] data_in;

    always @(posedge clk) begin
        if (rst) begin
            data_in <= 0;
        end
        else begin
            if (current_state == DATA) begin
                if (sck == 0) begin
                    if ((data_count >= 16) && (data_count <= 23)) begin
                        data_in <= {data_in[6:0],miso};
                    end
                    else begin
                        data_in <= data_in;
                    end
                end
                else begin
                    data_in <= data_in;
                end
            end
            else begin
                
            end
        end
    end

    assign ext_data_out = data_in;
    
    // Finite State Machine

    localparam IDLE = 2'b00;
    localparam ENABLE = 2'b01;
    localparam DATA = 2'b10;

    reg [1:0] current_state, next_state;

    always @(posedge clk) begin
        if (rst) begin
            current_state <= 0;
        end
        else begin
            current_state <= next_state;
        end
    end

    always @(*) begin
        if (rst) begin
            next_state = 0;
        end
        else begin
            case (current_state)
                IDLE: begin
                    cs = 1;
                    sck = 1;
                    mosi = 0;
                    if (en == 1'b1) begin
                        next_state = ENABLE;
                    end
                end
                ENABLE: begin
                    cs = 0;
                    sck = ~clock_count;
                    mosi = 0;
                    next_state = DATA;
                end
                DATA: begin
                    cs = 0;
                    sck = ~clock_count;
                    mosi = data_save[23];
                    if (data_end == 1'b1) begin
                        sck = 1;
                        next_state = IDLE;
                    end
                end
                default: next_state = IDLE;
            endcase
        end
    end

endmodule

Communication_Protocols/SPI/SPI_Master_tb.v
`timescale 1ns/1ns
`include "SPI_Master.v"

module spi_master_tb;
    
    reg clk;
    reg rst;
    // Chip Select
    reg en;
    wire cs;
    // Serial Clock
    wire sck;
    // Master Out Slave In
    reg [7:0] ext_command_in;
    reg [7:0] ext_address_in;
    reg [7:0] ext_data_in;
    wire mosi;
    // Master In Slave Out
    reg miso;
    wire [7:0] ext_data_out;

    spi_master uut (
        .clk (clk),
        .rst (rst),
        .en (en),
        .cs (cs),
        .sck (sck),
        .ext_command_in (ext_command_in),
        .ext_address_in (ext_address_in),
        .ext_data_in (ext_data_in),
        .mosi (mosi),
        .miso (miso),
        .ext_data_out (ext_data_out)
    );

    initial clk = 0;
    always #10 clk = ~clk;
    
    initial begin
        #10 rst = 1;
        #50 rst = 0;
        #50 ext_command_in = 8'ha5; ext_address_in = 8'h12; ext_data_in = 8'hed;
        #25 en = 1;
        #30 en = 0;
        #1500 ext_command_in = 8'h00; ext_address_in = 8'h34; ext_data_in = 8'hcb;
        #25 en = 1;
        #25 en = 0;
        #1500 ext_command_in = 8'hff; ext_address_in = 8'h67; ext_data_in = 8'h98;
        #30 en = 1;
        #30 en = 0;
        #1500 $finish;
    end
    
    initial begin
        $dumpfile("SPI_Master_tb.vcd");
        $dumpvars(0,spi_master_tb);
    end

endmodule

Communication_Protocols/SPI/SPI_Master_tb.vcd
$date
	Thu Nov 16 00:51:17 2023
$end
$version
	Icarus Verilog
$end
$timescale
	1ns
$end
$scope module spi_master_tb $end
$var wire 1 ! sck $end
$var wire 1 " mosi $end
$var wire 8 # ext_data_out [7:0] $end
$var wire 1 $ cs $end
$var reg 1 % clk $end
$var reg 1 & en $end
$var reg 8 ' ext_address_in [7:0] $end
$var reg 8 ( ext_command_in [7:0] $end
$var reg 8 ) ext_data_in [7:0] $end
$var reg 1 * miso $end
$var reg 1 + rst $end
$scope module uut $end
$var wire 1 % clk $end
$var wire 1 & en $end
$var wire 8 , ext_address_in [7:0] $end
$var wire 8 - ext_command_in [7:0] $end
$var wire 8 . ext_data_in [7:0] $end
$var wire 8 / ext_data_out [7:0] $end
$var wire 1 * miso $end
$var wire 1 + rst $end
$var reg 1 0 clock_count $end
$var reg 1 $ cs $end
$var reg 2 1 current_state [1:0] $end
$var reg 24 2 data_count [23:0] $end
$var reg 1 3 data_end $end
$var reg 8 4 data_in [7:0] $end
$var reg 24 5 data_save [23:0] $end
$var reg 1 " mosi $end
$var reg 2 6 next_state [1:0] $end
$var reg 1 ! sck $end
$upscope $end
$upscope $end
$enddefinitions $end
#0
$dumpvars
bx 6
bx 5
bx 4
x3
bx 2
bx 1
x0
bx /
bx .
bx -
bx ,
x+
x*
bx )
bx (
bx '
x&
0%
x$
bx #
x"
x!
$end
#10
00
03
b0 2
b0 5
b0 #
b0 /
b0 4
b0 1
b0 6
1+
1%
#20
0%
#30
1%
#40
0%
#50
1%
#60
0"
1!
1$
0%
0+
#70
bx00000000 5
1%
#80
0%
#90
1%
#100
0%
#110
b101001010001001000000000 5
1%
b11101101 )
b11101101 .
b10010 '
b10010 ,
b10100101 (
b10100101 -
#120
0%
#130
1%
#135
b1 6
1&
#140
0%
#150
b10 6
0$
b1 1
1%
#160
0%
#165
0&
#170
1"
0!
10
b10 1
1%
#180
0%
#190
1!
00
1%
#200
0%
#210
0"
0!
10
b1 2
b10010100010010000000000 5
1%
#220
0%
#230
1!
00
1%
#240
0%
#250
1"
0!
10
b10 2
b100101000100100000000000 5
1%
#260
0%
#270
1!
00
1%
#280
0%
#290
0"
0!
10
b11 2
b1010001001000000000000 5
1%
#300
0%
#310
1!
00
1%
#320
0%
#330
0!
10
b100 2
b10100010010000000000000 5
1%
#340
0%
#350
1!
00
1%
#360
0%
#370
1"
0!
10
b101 2
b101000100100000000000000 5
1%
#380
0%
#390
1!
00
1%
#400
0%
#410
0"
0!
10
b110 2
b10001001000000000000000 5
1%
#420
0%
#430
1!
00
1%
#440
0%
#450
1"
0!
10
b111 2
b100010010000000000000000 5
1%
#460
0%
#470
1!
00
1%
#480
0%
#490
0"
0!
10
b1000 2
b100100000000000000000 5
1%
#500
0%
#510
1!
00
1%
#520
0%
#530
0!
10
b1001 2
b1001000000000000000000 5
1%
#540
0%
#550
1!
00
1%
#560
0%
#570
0!
10
b1010 2
b10010000000000000000000 5
1%
#580
0%
#590
1!
00
1%
#600
0%
#610
1"
0!
10
b1011 2
b100100000000000000000000 5
1%
#620
0%
#630
1!
00
1%
#640
0%
#650
0"
0!
10
b1100 2
b1000000000000000000000 5
1%
#660
0%
#670
1!
00
1%
#680
0%
#690
0!
10
b1101 2
b10000000000000000000000 5
1%
#700
0%
#710
1!
00
1%
#720
0%
#730
1"
0!
10
b1110 2
b100000000000000000000000 5
1%
#740
0%
#750
1!
00
1%
#760
0%
#770
0"
0!
10
b1111 2
b0 5
1%
#780
0%
#790
1!
00
1%
#800
0%
#810
0!
10
b10000 2
1%
#820
0%
#830
1!
b0x #
b0x /
b0x 4
00
1%
#840
0%
#850
0!
10
b10001 2
1%
#860
0%
#870
1!
b0xx #
b0xx /
b0xx 4
00
1%
#880
0%
#890
0!
10
b10010 2
1%
#900
0%
#910
1!
b0xxx #
b0xxx /
b0xxx 4
00
1%
#920
0%
#930
0!
10
b10011 2
1%
#940
0%
#950
1!
b0xxxx #
b0xxxx /
b0xxxx 4
00
1%
#960
0%
#970
0!
10
b10100 2
1%
#980
0%
#990
1!
b0xxxxx #
b0xxxxx /
b0xxxxx 4
00
1%
#1000
0%
#1010
0!
10
b10101 2
1%
#1020
0%
#1030
1!
b0xxxxxx #
b0xxxxxx /
b0xxxxxx 4
00
1%
#1040
0%
#1050
0!
10
b10110 2
1%
#1060
0%
#1070
1!
b0xxxxxxx #
b0xxxxxxx /
b0xxxxxxx 4
00
1%
#1080
0%
#1090
0!
10
b10111 2
1%
#1100
0%
#1110
1!
bx #
bx /
bx 4
00
1%
#1120
0%
#1130
b0 6
1!
10
13
b0 2
1%
#1140
0%
#1150
1$
b0 1
03
b1 2
00
1%
#1160
0%
#1170
b0 2
b101001010001001000000000 5
1%
