Communication_Protocols/SPI/SPI_Slave.v
module spi_slave (
    input wire clk,
    input wire rst,
    // Chip Select
    input wire cs,
    // Serial Clock
    input wire sck,
    // Master Out Slave In
    input wire mosi,
    // Master In Slave Out
    output reg miso
);

    reg [23:0] data_count;
    reg data_end;

    always @(posedge clk) begin
        if (rst) begin
            data_count <= 0;
            data_end <= 0;
        end
        else begin
            if (current_state == DATA) begin
                if (sck == 1) begin
                    if (data_count == 23) begin
                        data_count <= 0;
                        data_end <= 1;
                    end
                    else begin
                        data_count <= data_count + 1;
                        data_end <= 0;
                    end
                end
                else begin
                    data_count <= data_count;
                    data_end <= 0;
                end
            end
            else begin
                data_count <= 0;
                data_end <= 0;
            end
        end
    end

    // Master Out Slave In

    reg [7:0] command_save;
    reg [7:0] address_save;
    reg [7:0] data_save;

    always @(posedge sck) begin
        if (rst) begin
            command_save <= 0;
            address_save <= 0;
            data_save <= 0;
        end
        else begin
            if (current_state == DATA) begin
                if ((data_count >= 0) && (data_count < 8)) begin
                    command_save <= {command_save[6:0],mosi};
                end
                else if ((data_count >= 8) && (data_count < 16)) begin
                    address_save <= {address_save[6:0],mosi};
                end
                else if ((data_count >= 16) && (data_count <= 23)) begin
                    data_save <= {data_save[6:0],mosi};
                end
                else begin
                    command_save <= command_save;
                    address_save <= address_save;
                    data_save <= data_save;
                end        
            end
            else begin
                command_save <= command_save;
                address_save <= address_save;
                data_save <= data_save;
            end
        end
    end

    // Master In Slave Out

    reg [7:0] data_out;

    always @(negedge sck) begin
        if (rst) begin
            data_out <= 0;
        end
        else begin
            if (current_state == DATA) begin
                if ((data_count > 1) && (data_count < 8)) begin
                    data_out <= data_save;
                end
                else if ((data_count >= 8) && (data_count <= 23)) begin
                    if ((data_count > 16) && (data_count <= 23)) begin
                        data_out <= {data_out[6:0],1'b0};
                    end
                    else begin
                        data_out <= data_out;
                    end
                end
                else begin
                    data_out <= data_out;
                end
            end
            else begin
                data_out <= data_out;
            end
        end
    end

    // Finite State Machine

    localparam IDLE = 2'b00;
    localparam DATA = 2'b10;
    localparam DISABLE = 2'b11;

    reg [1:0] current_state, next_state;

    always @(posedge clk) begin
        if (rst) begin
            current_state <= 0;
        end
        else begin
            current_state <= next_state;
        end
    end

    always @(*) begin
        if (rst) begin
            next_state = 0;
        end
        else begin
            case (next_state)
                IDLE: begin
                    miso = 0;
                    if (cs == 1'b0) begin
                        next_state = DATA;
                    end
                end
                DATA: begin
                    if ((data_count >= 16) && (data_count <= 23)) begin
                        if (command_save == 8'hff) begin
                            miso = data_out[7];
                        end
                        else begin
                            miso = 0;
                        end
                        
                    end
                    else begin
                        miso = 0;
                    end            
                    
                    if (data_end == 1'b1) begin
                        next_state = DISABLE;
                    end
                end
                DISABLE: begin
                    miso = 0;
                    if (cs == 1'b1) begin
                        next_state = IDLE;
                    end
                end
                default: next_state = IDLE;
            endcase
        end
    end

endmodule

Communication_Protocols/SPI/SPI_Master.v
module spi_master (
    input wire clk,
    input wire rst,
    // Chip Select
    input wire en,
    output reg cs,
    // Serial Clock
    output reg sck,
    // Master Out Slave In
    input wire [7:0] ext_command_in,
    input wire [7:0] ext_address_in,
    input wire [7:0] ext_data_in,
    output reg mosi,
    // Master In Slave Out
    input wire miso,
    output wire [7:0] ext_data_out
);
    
    // Serial Clock

    reg clock_count;

    always @(posedge clk) begin
        if (rst) begin
            clock_count <= 0;
        end
        else begin
            if ((current_state == ENABLE) || (current_state == DATA)) begin
                clock_count <= clock_count + 1;
            end
            else begin
                clock_count <= 0;
            end
        end
    end

    // Master Out Slave In

    reg [23:0] data_save;
    reg [23:0] data_count;
    reg data_end;

    always @(posedge clk) begin
        if (rst) begin
            data_save <= 0;
            data_count <= 0;
            data_end <= 0;
        end
        else begin
            if (current_state == DATA) begin
                if (sck == 1) begin
                    data_save <= {data_save[22:0],1'b0};
                    if (data_count == 23) begin
                        data_count <= 0;
                        data_end <= 1;
                    end
                    else begin
                        data_count <= data_count + 1;
                        data_end <= 0;
                    end
                end
                else begin
                    data_save <= data_save;
                    data_count <= data_count;
                    data_end <= 0;
                end
            end
            else begin
                if (ext_command_in == 8'h00) begin
                    data_save <= {ext_command_in,ext_address_in,ext_data_in};
                    data_count <= 0;
                    data_end <= 0;
                end
                else begin
                    data_save <= {ext_command_in,ext_address_in,8'h00};
                    data_count <= 0;
                    data_end <= 0;
                end
            end
        end
    end

    // Master In Slave Out

    reg [7:0] data_in;

    always @(posedge clk) begin
        if (rst) begin
            data_in <= 0;
        end
        else begin
            if (current_state == DATA) begin
                if (sck == 0) begin
                    if ((data_count >= 16) && (data_count <= 23)) begin
                        data_in <= {data_in[6:0],miso};
                    end
                    else begin
                        data_in <= data_in;
                    end
                end
                else begin
                    data_in <= data_in;
                end
            end
            else begin
                
            end
        end
    end

    assign ext_data_out = data_in;
    
    // Finite State Machine

    localparam IDLE = 2'b00;
    localparam ENABLE = 2'b01;
    localparam DATA = 2'b10;

    reg [1:0] current_state, next_state;

    always @(posedge clk) begin
        if (rst) begin
            current_state <= 0;
        end
        else begin
            current_state <= next_state;
        end
    end

    always @(*) begin
        if (rst) begin
            next_state = 0;
        end
        else begin
            case (current_state)
                IDLE: begin
                    cs = 1;
                    sck = 1;
                    mosi = 0;
                    if (en == 1'b1) begin
                        next_state = ENABLE;
                    end
                end
                ENABLE: begin
                    cs = 0;
                    sck = ~clock_count;
                    mosi = 0;
                    next_state = DATA;
                end
                DATA: begin
                    cs = 0;
                    sck = ~clock_count;
                    mosi = data_save[23];
                    if (data_end == 1'b1) begin
                        sck = 1;
                        next_state = IDLE;
                    end
                end
                default: next_state = IDLE;
            endcase
        end
    end

endmodule

Communication_Protocols/SPI/SPI.v
`include "SPI_Master.v"
`include "SPI_Slave.v"

module spi (
    input wire clk,
    input wire rst,
    input wire en,
    input wire [7:0] ext_command_in,
    input wire [7:0] ext_address_in,
    input wire [7:0] ext_data_in,
    output wire [7:0] ext_data_out
);
    
    wire cs;
    wire sck;
    wire mosi;
    wire miso;

    spi_master uut_master (
        .clk (clk),
        .rst (rst),
        .en (en),
        .cs (cs),
        .sck (sck),
        .ext_command_in (ext_command_in),
        .ext_address_in (ext_address_in),
        .ext_data_in (ext_data_in),
        .mosi (mosi),
        .miso (miso),
        .ext_data_out (ext_data_out)
    );

    spi_slave uut_slave (
        .clk (clk),
        .rst (rst),
        .cs (cs),
        .sck (sck),
        .mosi (mosi),
        .miso (miso)
    );

endmodule

Communication_Protocols/SPI/SPI_tb.v
`timescale 1ns/1ns
`include "SPI.v"

module spi_tb;
    
    reg clk;
    reg rst;
    reg en;
    reg [7:0] ext_command_in;
    reg [7:0] ext_address_in;
    reg [7:0] ext_data_in;
    output wire [7:0] ext_data_out;

    spi uut (
        .clk (clk),
        .rst (rst),
        .en (en),
        .ext_command_in (ext_command_in),
        .ext_address_in (ext_address_in),
        .ext_data_in (ext_data_in),
        .ext_data_out (ext_data_out)
    );

    initial clk = 0;
    always #10 clk = ~clk;
    
    initial begin
        #10 rst = 1;
        #50 rst = 0;
        #50 ext_command_in = 8'ha5; ext_address_in = 8'h12; ext_data_in = 8'hed;
        #25 en = 1;
        #30 en = 0;
        #1500 ext_command_in = 8'h00; ext_address_in = 8'h34; ext_data_in = 8'hcb;
        #25 en = 1;
        #25 en = 0;
        #1500 ext_command_in = 8'hff; ext_address_in = 8'h67; ext_data_in = 8'h98;
        #30 en = 1;
        #30 en = 0;
        #1500 ext_command_in = 8'h00; ext_address_in = 8'h12; ext_data_in = 8'hed;
        #25 en = 1;
        #30 en = 0;
        #1500 ext_command_in = 8'hff; ext_address_in = 8'h34; ext_data_in = 8'hcb;
        #25 en = 1;
        #25 en = 0;
        #1500 ext_command_in = 8'ha5; ext_address_in = 8'h67; ext_data_in = 8'h98;
        #30 en = 1;
        #30 en = 0;
        #1500 $finish;
    end

    initial begin
        $dumpfile("SPI_tb.vcd");
        $dumpvars(0,spi_tb);
    end

endmodule

Communication_Protocols/SPI/SPI_tb.vcd
$date
	Thu Nov 16 00:52:08 2023
$end
$version
	Icarus Verilog
$end
$timescale
	1ns
$end
$scope module spi_tb $end
$var wire 8 ! ext_data_out [7:0] $end
$var reg 1 " clk $end
$var reg 1 # en $end
$var reg 8 $ ext_address_in [7:0] $end
$var reg 8 % ext_command_in [7:0] $end
$var reg 8 & ext_data_in [7:0] $end
$var reg 1 ' rst $end
$scope module uut $end
$var wire 1 " clk $end
$var wire 1 # en $end
$var wire 8 ( ext_address_in [7:0] $end
$var wire 8 ) ext_command_in [7:0] $end
$var wire 8 * ext_data_in [7:0] $end
$var wire 1 ' rst $end
$var wire 1 + sck $end
$var wire 1 , mosi $end
$var wire 1 - miso $end
$var wire 8 . ext_data_out [7:0] $end
$var wire 1 / cs $end
$scope module uut_master $end
$var wire 1 " clk $end
$var wire 1 # en $end
$var wire 8 0 ext_address_in [7:0] $end
$var wire 8 1 ext_command_in [7:0] $end
$var wire 8 2 ext_data_in [7:0] $end
$var wire 8 3 ext_data_out [7:0] $end
$var wire 1 ' rst $end
$var wire 1 - miso $end
$var reg 1 4 clock_count $end
$var reg 1 / cs $end
$var reg 2 5 current_state [1:0] $end
$var reg 24 6 data_count [23:0] $end
$var reg 1 7 data_end $end
$var reg 8 8 data_in [7:0] $end
$var reg 24 9 data_save [23:0] $end
$var reg 1 , mosi $end
$var reg 2 : next_state [1:0] $end
$var reg 1 + sck $end
$upscope $end
$scope module uut_slave $end
$var wire 1 " clk $end
$var wire 1 / cs $end
$var wire 1 , mosi $end
$var wire 1 ' rst $end
$var wire 1 + sck $end
$var reg 8 ; address_save [7:0] $end
$var reg 8 < command_save [7:0] $end
$var reg 2 = current_state [1:0] $end
$var reg 24 > data_count [23:0] $end
$var reg 1 ? data_end $end
$var reg 8 @ data_out [7:0] $end
$var reg 8 A data_save [7:0] $end
$var reg 1 - miso $end
$var reg 2 B next_state [1:0] $end
$upscope $end
$upscope $end
$upscope $end
$enddefinitions $end
#0
$dumpvars
bx B
bx A
bx @
x?
bx >
bx =
bx <
bx ;
bx :
bx 9
bx 8
x7
bx 6
bx 5
x4
bx 3
bx 2
bx 1
bx 0
x/
bx .
x-
x,
x+
bx *
bx )
bx (
x'
bx &
bx %
bx $
x#
0"
bx !
$end
#10
04
07
b0 6
b0 9
b0 !
b0 .
b0 3
b0 8
b0 5
0?
b0 >
b0 =
b0 :
b0 B
1'
1"
#20
0"
#30
1"
#40
0"
#50
1"
#60
0,
1+
1/
0-
0"
0'
#70
bx00000000 9
1"
#80
0"
#90
1"
#100
0"
#110
b101001010001001000000000 9
1"
b11101101 &
b11101101 *
b11101101 2
b10010 $
b10010 (
b10010 0
b10100101 %
b10100101 )
b10100101 1
#120
0"
#130
1"
#135
b1 :
1#
#140
0"
#150
b10 B
b10 :
0/
b1 5
1"
#160
0"
#165
0#
#170
1,
0+
14
b10 5
b10 =
1"
#180
0"
#190
bx1 <
1+
04
1"
#200
0"
#210
0,
0+
14
b1 6
b10010100010010000000000 9
b1 >
1"
#220
0"
#230
bx10 <
1+
04
1"
#240
0"
#250
1,
0+
14
b10 6
b100101000100100000000000 9
b10 >
1"
#260
0"
#270
bx101 <
1+
04
1"
#280
0"
#290
0,
0+
14
b11 6
b1010001001000000000000 9
b11 >
1"
#300
0"
#310
bx1010 <
1+
04
1"
#320
0"
#330
0+
14
b100 6
b10100010010000000000000 9
b100 >
1"
#340
0"
#350
bx10100 <
1+
04
1"
#360
0"
#370
1,
0+
14
b101 6
b101000100100000000000000 9
b101 >
1"
#380
0"
#390
bx101001 <
1+
04
1"
#400
0"
#410
0,
0+
14
b110 6
b10001001000000000000000 9
b110 >
1"
#420
0"
#430
bx1010010 <
1+
04
1"
#440
0"
#450
1,
0+
14
b111 6
b100010010000000000000000 9
b111 >
1"
#460
0"
#470
b10100101 <
1+
04
1"
#480
0"
#490
0,
0+
14
b1000 6
b100100000000000000000 9
b1000 >
1"
#500
0"
#510
bx0 ;
1+
04
1"
#520
0"
#530
0+
14
b1001 6
b1001000000000000000000 9
b1001 >
1"
#540
0"
#550
bx00 ;
1+
04
1"
#560
0"
#570
0+
14
b1010 6
b10010000000000000000000 9
b1010 >
1"
#580
0"
#590
bx000 ;
1+
04
1"
#600
0"
#610
1,
0+
14
b1011 6
b100100000000000000000000 9
b1011 >
1"
#620
0"
#630
bx0001 ;
1+
04
1"
#640
0"
#650
0,
0+
14
b1100 6
b1000000000000000000000 9
b1100 >
1"
#660
0"
#670
bx00010 ;
1+
04
1"
#680
0"
#690
0+
14
b1101 6
b10000000000000000000000 9
b1101 >
1"
#700
0"
#710
bx000100 ;
1+
04
1"
#720
0"
#730
1,
0+
14
b1110 6
b100000000000000000000000 9
b1110 >
1"
#740
0"
#750
bx0001001 ;
1+
04
1"
#760
0"
#770
0,
0+
14
b1111 6
b0 9
b1111 >
1"
#780
0"
#790
b10010 ;
1+
04
1"
#800
0"
#810
0+
14
b10000 6
b10000 >
1"
#820
0"
#830
bx0 A
1+
04
1"
#840
0"
#850
bx0 @
0+
14
b10001 6
b10001 >
1"
#860
0"
#870
bx00 A
1+
04
1"
#880
0"
#890
bx00 @
0+
14
b10010 6
b10010 >
1"
#900
0"
#910
bx000 A
1+
04
1"
#920
0"
#930
bx000 @
0+
14
b10011 6
b10011 >
1"
#940
0"
#950
bx0000 A
1+
04
1"
#960
0"
#970
bx0000 @
0+
14
b10100 6
b10100 >
1"
#980
0"
#990
bx00000 A
1+
04
1"
#1000
0"
#1010
bx00000 @
0+
14
b10101 6
b10101 >
1"
#1020
0"
#1030
bx000000 A
1+
04
1"
#1040
0"
#1050
bx000000 @
0+
14
b10110 6
b10110 >
1"
#1060
0"
#1070
bx0000000 A
1+
04
1"
#1080
0"
#1090
bx0000000 @
0+
14
b10111 6
b10111 >
1"
#1100
0"
#1110
b0 A
1+
04
1"
#1120
0"
#1130
b1001010 <
b0 :
1+
b11 B
14
17
b0 6
1?
b0 >
1"
#1140
0"
#1150
b0 B
1/
b11 =
0?
b1 >
b0 5
07
b1 6
04
1"
#1160
0"
#1170
b0 6
b101001010001001000000000 9
b0 >
b0 =
1"
